argophor/__init__.py
argophor/curl_wget_gpg_depd/__init__.py
argophor/curl_wget_gpg_depd/allinone.py
argophor/curl_wget_gpg_depd/detector.py
argophor/curl_wget_gpg_depd/installer.py
argophor/flatpak_depd/__init__.py
argophor/flatpak_depd/allinone.py
argophor/flatpak_depd/detector.py
argophor/flatpak_depd/installer.py
argophor/sdkman_depd/__init__.py
argophor/sdkman_depd/allinone.py
argophor/sdkman_depd/depresolver.py
argophor/sdkman_depd/detector.py
argophor/sdkman_depd/installer.py
argophor/snap_depd/__init__.py
argophor/snap_depd/allinone.py
argophor/snap_depd/detector.py
argophor/snap_depd/installer.py
argophor-0.0.1a8.dist-info/licenses/LICENSE
argophor-0.0.1a8.dist-info/METADATA
argophor-0.0.1a8.dist-info/WHEEL
argophor-0.0.1a8.dist-info/top_level.txt
argophor-0.0.1a8.dist-info/RECORD
