Metadata-Version: 2.4
Name: argophor
Version: 0.0.1a8
Summary: Argophor - detection and install helper tool
Home-page: https://github.com/hejhdiss/argophor
Author: Muhammed Shafin P
Author-email: hejhdiss@gmail.com
License: Argophor License 1.0
Classifier: Programming Language :: Python :: 3
Classifier: License :: Other/Proprietary License
Classifier: Operating System :: POSIX :: Linux
Requires-Python: >=3.6
License-File: LICENSE
Dynamic: author
Dynamic: author-email
Dynamic: classifier
Dynamic: description
Dynamic: description-content-type
Dynamic: home-page
Dynamic: license
Dynamic: license-file
Dynamic: requires-python
Dynamic: summary
